mcworldlib/__init__.py
mcworldlib/anvil.py
mcworldlib/chunk.py
mcworldlib/cli.py
mcworldlib/entity.py
mcworldlib/level.py
mcworldlib/nbt.py
mcworldlib/player.py
mcworldlib/tree.py
mcworldlib/util.py
mcworldlib/world.py
mcworldlib-2023.7.13.dist-info/LICENSE
mcworldlib-2023.7.13.dist-info/METADATA
mcworldlib-2023.7.13.dist-info/WHEEL
mcworldlib-2023.7.13.dist-info/top_level.txt
mcworldlib-2023.7.13.dist-info/RECORD
