Metadata-Version: 2.1
Name: mcworldlib
Version: 2023.7.13
Summary: Yet another python library to manipulate Minecraft save data
Home-page: https://github.com/MestreLion/mcworldlib
Author: Rodrigo Silva (MestreLion)
Author-email: minecraft@rodrigosilva.com
License: GPLv3+
Project-URL: Bug Tracker, https://github.com/MestreLion/mcworldlib/issues
Project-URL: Source Code, https://github.com/MestreLion/mcworldlib
Keywords: minecraft,save,nbt,chunk,region,world,library
Classifier: Development Status :: 1 - Planning
Classifier: Intended Audience :: Developers
Classifier: License :: OSI Approved :: GNU General Public License v3 or later (GPLv3+)
Classifier: Natural Language :: English
Classifier: Operating System :: OS Independent
Classifier: Programming Language :: Python
Classifier: Programming Language :: Python :: 3
Classifier: Programming Language :: Python :: 3.8
Classifier: Programming Language :: Python :: 3.9
Classifier: Programming Language :: Python :: 3.10
Classifier: Programming Language :: Python :: 3.11
Classifier: Topic :: Games/Entertainment
Classifier: Topic :: Software Development :: Libraries :: Python Modules
Requires-Python: >=3.8
License-File: LICENSE
Requires-Dist: nbtlib (>=2.0.4)
Requires-Dist: numpy
Requires-Dist: tqdm
